<class>
  <keyword> class </keyword>
  <identifier> Math </identifier>
  <symbol> { </symbol>
  <classVarDec>
    <keyword> static </keyword>
    <identifier> Array </identifier>
    <identifier> bitmask </identifier>
    <symbol> ; </symbol>
  </classVarDec>
  <subroutineDec>
    <keyword> function </keyword>
    <keyword> void </keyword>
    <identifier> init </identifier>
    <symbol> ( </symbol>
    <parameterList>
    </parameterList>
    <symbol> ) </symbol>
    <subroutineBody>
      <symbol> { </symbol>
      <varDec>
        <keyword> var </keyword>
        <keyword> int </keyword>
        <identifier> m </identifier>
        <symbol> , </symbol>
        <identifier> index </identifier>
        <symbol> ; </symbol>
      </varDec>
      <statements>
        <letStatement>
          <keyword> let </keyword>
          <identifier> bitmask </identifier>
          <symbol> = </symbol>
          <expression>
            <term>
              <subroutineCall>
                <identifier> Array </identifier>
                <symbol> . </symbol>
                <identifier> new </identifier>
                <symbol> ( </symbol>
                <expressionList>
                  <expression>
                    <term>
                      <integerConstant> 16 </integerConstant>
                    </term>
                  </expression>
                </expressionList>
                <symbol> ) </symbol>
              </subroutineCall>
            </term>
          </expression>
          <symbol> ; </symbol>
        </letStatement>
        <letStatement>
          <keyword> let </keyword>
          <identifier> m </identifier>
          <symbol> = </symbol>
          <expression>
            <term>
              <integerConstant> 1 </integerConstant>
            </term>
          </expression>
          <symbol> ; </symbol>
        </letStatement>
        <letStatement>
          <keyword> let </keyword>
          <identifier> index </identifier>
          <symbol> = </symbol>
          <expression>
            <term>
              <integerConstant> 0 </integerConstant>
            </term>
          </expression>
          <symbol> ; </symbol>
        </letStatement>
        <whileStatement>
          <keyword> while </keyword>
          <symbol> ( </symbol>
          <expression>
            <term>
              <identifier> index </identifier>
            </term>
            <symbol> &lt; </symbol>
            <term>
              <integerConstant> 16 </integerConstant>
            </term>
          </expression>
          <symbol> ) </symbol>
          <symbol> { </symbol>
          <statements>
            <letStatement>
              <keyword> let </keyword>
              <identifier> bitmask </identifier>
              <arrayAccess>
                <symbol> [ </symbol>
                <expression>
                  <term>
                    <identifier> index </identifier>
                  </term>
                </expression>
                <symbol> ] </symbol>
              </arrayAccess>
              <symbol> = </symbol>
              <expression>
                <term>
                  <identifier> m </identifier>
                </term>
              </expression>
              <symbol> ; </symbol>
            </letStatement>
            <letStatement>
              <keyword> let </keyword>
              <identifier> m </identifier>
              <symbol> = </symbol>
              <expression>
                <term>
                  <identifier> m </identifier>
                </term>
                <symbol> + </symbol>
                <term>
                  <identifier> m </identifier>
                </term>
              </expression>
              <symbol> ; </symbol>
            </letStatement>
            <letStatement>
              <keyword> let </keyword>
              <identifier> index </identifier>
              <symbol> = </symbol>
              <expression>
                <term>
                  <identifier> index </identifier>
                </term>
                <symbol> + </symbol>
                <term>
                  <integerConstant> 1 </integerConstant>
                </term>
              </expression>
              <symbol> ; </symbol>
            </letStatement>
          </statements>
          <symbol> } </symbol>
        </whileStatement>
        <returnStatement>
          <keyword> return </keyword>
          <symbol> ; </symbol>
        </returnStatement>
      </statements>
      <symbol> } </symbol>
    </subroutineBody>
  </subroutineDec>
  <subroutineDec>
    <keyword> function </keyword>
    <keyword> int </keyword>
    <identifier> abs </identifier>
    <symbol> ( </symbol>
    <parameterList>
      <keyword> int </keyword>
      <identifier> x </identifier>
    </parameterList>
    <symbol> ) </symbol>
    <subroutineBody>
      <symbol> { </symbol>
      <statements>
        <ifStatement>
          <keyword> if </keyword>
          <symbol> ( </symbol>
          <expression>
            <term>
              <identifier> x </identifier>
            </term>
            <symbol> &gt; </symbol>
            <term>
              <integerConstant> 0 </integerConstant>
            </term>
          </expression>
          <symbol> ) </symbol>
          <symbol> { </symbol>
          <statements>
            <returnStatement>
              <keyword> return </keyword>
              <expression>
                <term>
                  <identifier> x </identifier>
                </term>
              </expression>
              <symbol> ; </symbol>
            </returnStatement>
          </statements>
          <symbol> } </symbol>
        </ifStatement>
        <returnStatement>
          <keyword> return </keyword>
          <expression>
            <term>
              <symbol> ( </symbol>
              <expression>
                <term>
                  <integerConstant> 0 </integerConstant>
                </term>
                <symbol> - </symbol>
                <term>
                  <identifier> x </identifier>
                </term>
              </expression>
              <symbol> ) </symbol>
            </term>
          </expression>
          <symbol> ; </symbol>
        </returnStatement>
      </statements>
      <symbol> } </symbol>
    </subroutineBody>
  </subroutineDec>
  <subroutineDec>
    <keyword> function </keyword>
    <keyword> int </keyword>
    <identifier> multiply </identifier>
    <symbol> ( </symbol>
    <parameterList>
      <keyword> int </keyword>
      <identifier> x </identifier>
      <symbol> , </symbol>
      <keyword> int </keyword>
      <identifier> y </identifier>
    </parameterList>
    <symbol> ) </symbol>
    <subroutineBody>
      <symbol> { </symbol>
      <varDec>
        <keyword> var </keyword>
        <keyword> int </keyword>
        <identifier> sum </identifier>
        <symbol> , </symbol>
        <identifier> shiftedX </identifier>
        <symbol> , </symbol>
        <identifier> i </identifier>
        <symbol> ; </symbol>
      </varDec>
      <statements>
        <letStatement>
          <keyword> let </keyword>
          <identifier> sum </identifier>
          <symbol> = </symbol>
          <expression>
            <term>
              <integerConstant> 0 </integerConstant>
            </term>
          </expression>
          <symbol> ; </symbol>
        </letStatement>
        <letStatement>
          <keyword> let </keyword>
          <identifier> shiftedX </identifier>
          <symbol> = </symbol>
          <expression>
            <term>
              <identifier> x </identifier>
            </term>
          </expression>
          <symbol> ; </symbol>
        </letStatement>
        <letStatement>
          <keyword> let </keyword>
          <identifier> i </identifier>
          <symbol> = </symbol>
          <expression>
            <term>
              <integerConstant> 0 </integerConstant>
            </term>
          </expression>
          <symbol> ; </symbol>
        </letStatement>
        <whileStatement>
          <keyword> while </keyword>
          <symbol> ( </symbol>
          <expression>
            <term>
              <identifier> i </identifier>
            </term>
            <symbol> &lt; </symbol>
            <term>
              <integerConstant> 16 </integerConstant>
            </term>
          </expression>
          <symbol> ) </symbol>
          <symbol> { </symbol>
          <statements>
            <ifStatement>
              <keyword> if </keyword>
              <symbol> ( </symbol>
              <expression>
                <term>
                  <subroutineCall>
                    <identifier> Math </identifier>
                    <symbol> . </symbol>
                    <identifier> ithbit </identifier>
                    <symbol> ( </symbol>
                    <expressionList>
                      <expression>
                        <term>
                          <identifier> y </identifier>
                        </term>
                      </expression>
                      <symbol> , </symbol>
                      <expression>
                        <term>
                          <identifier> i </identifier>
                        </term>
                      </expression>
                    </expressionList>
                    <symbol> ) </symbol>
                  </subroutineCall>
                </term>
                <symbol> &gt; </symbol>
                <term>
                  <integerConstant> 0 </integerConstant>
                </term>
              </expression>
              <symbol> ) </symbol>
              <symbol> { </symbol>
              <statements>
                <letStatement>
                  <keyword> let </keyword>
                  <identifier> sum </identifier>
                  <symbol> = </symbol>
                  <expression>
                    <term>
                      <identifier> sum </identifier>
                    </term>
                    <symbol> + </symbol>
                    <term>
                      <identifier> shiftedX </identifier>
                    </term>
                  </expression>
                  <symbol> ; </symbol>
                </letStatement>
              </statements>
              <symbol> } </symbol>
            </ifStatement>
            <letStatement>
              <keyword> let </keyword>
              <identifier> shiftedX </identifier>
              <symbol> = </symbol>
              <expression>
                <term>
                  <identifier> shiftedX </identifier>
                </term>
                <symbol> + </symbol>
                <term>
                  <identifier> shiftedX </identifier>
                </term>
              </expression>
              <symbol> ; </symbol>
            </letStatement>
            <letStatement>
              <keyword> let </keyword>
              <identifier> i </identifier>
              <symbol> = </symbol>
              <expression>
                <term>
                  <identifier> i </identifier>
                </term>
                <symbol> + </symbol>
                <term>
                  <integerConstant> 1 </integerConstant>
                </term>
              </expression>
              <symbol> ; </symbol>
            </letStatement>
          </statements>
          <symbol> } </symbol>
        </whileStatement>
        <doStatement>
          <keyword> do </keyword>
          <subroutineCall>
            <identifier> Output </identifier>
            <symbol> . </symbol>
            <identifier> printString </identifier>
            <symbol> ( </symbol>
            <expressionList>
              <expression>
                <term>
                  <stringConstant> sum: </stringConstant>
                </term>
              </expression>
            </expressionList>
            <symbol> ) </symbol>
          </subroutineCall>
          <symbol> ; </symbol>
        </doStatement>
        <doStatement>
          <keyword> do </keyword>
          <subroutineCall>
            <identifier> Output </identifier>
            <symbol> . </symbol>
            <identifier> printInt </identifier>
            <symbol> ( </symbol>
            <expressionList>
              <expression>
                <term>
                  <identifier> sum </identifier>
                </term>
              </expression>
            </expressionList>
            <symbol> ) </symbol>
          </subroutineCall>
          <symbol> ; </symbol>
        </doStatement>
        <doStatement>
          <keyword> do </keyword>
          <subroutineCall>
            <identifier> Output </identifier>
            <symbol> . </symbol>
            <identifier> println </identifier>
            <symbol> ( </symbol>
            <expressionList>
            </expressionList>
            <symbol> ) </symbol>
          </subroutineCall>
          <symbol> ; </symbol>
        </doStatement>
        <returnStatement>
          <keyword> return </keyword>
          <expression>
            <term>
              <identifier> sum </identifier>
            </term>
          </expression>
          <symbol> ; </symbol>
        </returnStatement>
      </statements>
      <symbol> } </symbol>
    </subroutineBody>
  </subroutineDec>
  <subroutineDec>
    <keyword> function </keyword>
    <keyword> int </keyword>
    <identifier> ithbit </identifier>
    <symbol> ( </symbol>
    <parameterList>
      <keyword> int </keyword>
      <identifier> number </identifier>
      <symbol> , </symbol>
      <keyword> int </keyword>
      <identifier> i </identifier>
    </parameterList>
    <symbol> ) </symbol>
    <subroutineBody>
      <symbol> { </symbol>
      <statements>
        <ifStatement>
          <keyword> if </keyword>
          <symbol> ( </symbol>
          <expression>
            <term>
              <symbol> ( </symbol>
              <expression>
                <term>
                  <identifier> i </identifier>
                </term>
                <symbol> &gt; </symbol>
                <term>
                  <symbol> - </symbol>
                  <term>
                    <integerConstant> 1 </integerConstant>
                  </term>
                </term>
              </expression>
              <symbol> ) </symbol>
            </term>
            <symbol> &amp; </symbol>
            <term>
              <symbol> ( </symbol>
              <expression>
                <term>
                  <identifier> i </identifier>
                </term>
                <symbol> &lt; </symbol>
                <term>
                  <integerConstant> 16 </integerConstant>
                </term>
              </expression>
              <symbol> ) </symbol>
            </term>
          </expression>
          <symbol> ) </symbol>
          <symbol> { </symbol>
          <statements>
            <doStatement>
              <keyword> do </keyword>
              <subroutineCall>
                <identifier> Output </identifier>
                <symbol> . </symbol>
                <identifier> printString </identifier>
                <symbol> ( </symbol>
                <expressionList>
                  <expression>
                    <term>
                      <stringConstant> number: </stringConstant>
                    </term>
                  </expression>
                </expressionList>
                <symbol> ) </symbol>
              </subroutineCall>
              <symbol> ; </symbol>
            </doStatement>
            <doStatement>
              <keyword> do </keyword>
              <subroutineCall>
                <identifier> Output </identifier>
                <symbol> . </symbol>
                <identifier> printInt </identifier>
                <symbol> ( </symbol>
                <expressionList>
                  <expression>
                    <term>
                      <identifier> number </identifier>
                    </term>
                  </expression>
                </expressionList>
                <symbol> ) </symbol>
              </subroutineCall>
              <symbol> ; </symbol>
            </doStatement>
            <doStatement>
              <keyword> do </keyword>
              <subroutineCall>
                <identifier> Output </identifier>
                <symbol> . </symbol>
                <identifier> printString </identifier>
                <symbol> ( </symbol>
                <expressionList>
                  <expression>
                    <term>
                      <stringConstant> , </stringConstant>
                    </term>
                  </expression>
                </expressionList>
                <symbol> ) </symbol>
              </subroutineCall>
              <symbol> ; </symbol>
            </doStatement>
            <doStatement>
              <keyword> do </keyword>
              <subroutineCall>
                <identifier> Output </identifier>
                <symbol> . </symbol>
                <identifier> printString </identifier>
                <symbol> ( </symbol>
                <expressionList>
                  <expression>
                    <term>
                      <stringConstant> i: </stringConstant>
                    </term>
                  </expression>
                </expressionList>
                <symbol> ) </symbol>
              </subroutineCall>
              <symbol> ; </symbol>
            </doStatement>
            <doStatement>
              <keyword> do </keyword>
              <subroutineCall>
                <identifier> Output </identifier>
                <symbol> . </symbol>
                <identifier> printInt </identifier>
                <symbol> ( </symbol>
                <expressionList>
                  <expression>
                    <term>
                      <identifier> i </identifier>
                    </term>
                  </expression>
                </expressionList>
                <symbol> ) </symbol>
              </subroutineCall>
              <symbol> ; </symbol>
            </doStatement>
            <doStatement>
              <keyword> do </keyword>
              <subroutineCall>
                <identifier> Output </identifier>
                <symbol> . </symbol>
                <identifier> printString </identifier>
                <symbol> ( </symbol>
                <expressionList>
                  <expression>
                    <term>
                      <stringConstant> , </stringConstant>
                    </term>
                  </expression>
                </expressionList>
                <symbol> ) </symbol>
              </subroutineCall>
              <symbol> ; </symbol>
            </doStatement>
            <doStatement>
              <keyword> do </keyword>
              <subroutineCall>
                <identifier> Output </identifier>
                <symbol> . </symbol>
                <identifier> printString </identifier>
                <symbol> ( </symbol>
                <expressionList>
                  <expression>
                    <term>
                      <stringConstant> bitmask[i]: </stringConstant>
                    </term>
                  </expression>
                </expressionList>
                <symbol> ) </symbol>
              </subroutineCall>
              <symbol> ; </symbol>
            </doStatement>
            <doStatement>
              <keyword> do </keyword>
              <subroutineCall>
                <identifier> Output </identifier>
                <symbol> . </symbol>
                <identifier> printInt </identifier>
                <symbol> ( </symbol>
                <expressionList>
                  <expression>
                    <term>
                      <identifier> mask </identifier>
                      <arrayAccess>
                        <symbol> [ </symbol>
                        <expression>
                          <term>
                            <identifier> i </identifier>
                          </term>
                        </expression>
                        <symbol> ] </symbol>
                      </arrayAccess>
                    </term>
                  </expression>
                </expressionList>
                <symbol> ) </symbol>
              </subroutineCall>
              <symbol> ; </symbol>
            </doStatement>
            <doStatement>
              <keyword> do </keyword>
              <subroutineCall>
                <identifier> Output </identifier>
                <symbol> . </symbol>
                <identifier> println </identifier>
                <symbol> ( </symbol>
                <expressionList>
                </expressionList>
                <symbol> ) </symbol>
              </subroutineCall>
              <symbol> ; </symbol>
            </doStatement>
            <returnStatement>
              <keyword> return </keyword>
              <expression>
                <term>
                  <symbol> ( </symbol>
                  <expression>
                    <term>
                      <identifier> number </identifier>
                    </term>
                    <symbol> &amp; </symbol>
                    <term>
                      <identifier> bitmask </identifier>
                      <arrayAccess>
                        <symbol> [ </symbol>
                        <expression>
                          <term>
                            <identifier> i </identifier>
                          </term>
                        </expression>
                        <symbol> ] </symbol>
                      </arrayAccess>
                    </term>
                  </expression>
                  <symbol> ) </symbol>
                </term>
              </expression>
              <symbol> ; </symbol>
            </returnStatement>
          </statements>
          <symbol> } </symbol>
        </ifStatement>
        <returnStatement>
          <keyword> return </keyword>
          <expression>
            <term>
              <integerConstant> 0 </integerConstant>
            </term>
          </expression>
          <symbol> ; </symbol>
        </returnStatement>
      </statements>
      <symbol> } </symbol>
    </subroutineBody>
  </subroutineDec>
  <subroutineDec>
    <keyword> function </keyword>
    <keyword> int </keyword>
    <identifier> divide </identifier>
    <symbol> ( </symbol>
    <parameterList>
      <keyword> int </keyword>
      <identifier> x </identifier>
      <symbol> , </symbol>
      <keyword> int </keyword>
      <identifier> y </identifier>
    </parameterList>
    <symbol> ) </symbol>
    <subroutineBody>
      <symbol> { </symbol>
      <varDec>
        <keyword> var </keyword>
        <keyword> int </keyword>
        <identifier> q </identifier>
        <symbol> ; </symbol>
      </varDec>
      <statements>
        <ifStatement>
          <keyword> if </keyword>
          <symbol> ( </symbol>
          <expression>
            <term>
              <identifier> y </identifier>
            </term>
            <symbol> &gt; </symbol>
            <term>
              <identifier> x </identifier>
            </term>
          </expression>
          <symbol> ) </symbol>
          <symbol> { </symbol>
          <statements>
            <returnStatement>
              <keyword> return </keyword>
              <expression>
                <term>
                  <integerConstant> 0 </integerConstant>
                </term>
              </expression>
              <symbol> ; </symbol>
            </returnStatement>
          </statements>
          <symbol> } </symbol>
        </ifStatement>
        <letStatement>
          <keyword> let </keyword>
          <identifier> q </identifier>
          <symbol> = </symbol>
          <expression>
            <term>
              <subroutineCall>
                <identifier> divide </identifier>
                <symbol> ( </symbol>
                <expressionList>
                  <expression>
                    <term>
                      <identifier> x </identifier>
                    </term>
                  </expression>
                  <symbol> , </symbol>
                  <expression>
                    <term>
                      <identifier> y </identifier>
                    </term>
                    <symbol> + </symbol>
                    <term>
                      <identifier> y </identifier>
                    </term>
                  </expression>
                </expressionList>
                <symbol> ) </symbol>
              </subroutineCall>
            </term>
          </expression>
          <symbol> ; </symbol>
        </letStatement>
        <ifStatement>
          <keyword> if </keyword>
          <symbol> ( </symbol>
          <expression>
            <term>
              <symbol> ( </symbol>
              <expression>
                <term>
                  <identifier> x </identifier>
                </term>
                <symbol> - </symbol>
                <term>
                  <symbol> ( </symbol>
                  <expression>
                    <term>
                      <integerConstant> 2 </integerConstant>
                    </term>
                    <symbol> * </symbol>
                    <term>
                      <identifier> q </identifier>
                    </term>
                    <symbol> * </symbol>
                    <term>
                      <identifier> y </identifier>
                    </term>
                  </expression>
                  <symbol> ) </symbol>
                </term>
              </expression>
              <symbol> ) </symbol>
            </term>
            <symbol> &lt; </symbol>
            <term>
              <identifier> y </identifier>
            </term>
          </expression>
          <symbol> ) </symbol>
          <symbol> { </symbol>
          <statements>
            <returnStatement>
              <keyword> return </keyword>
              <expression>
                <term>
                  <identifier> q </identifier>
                </term>
                <symbol> + </symbol>
                <term>
                  <identifier> q </identifier>
                </term>
              </expression>
              <symbol> ; </symbol>
            </returnStatement>
          </statements>
          <symbol> } </symbol>
        </ifStatement>
        <returnStatement>
          <keyword> return </keyword>
          <expression>
            <term>
              <identifier> q </identifier>
            </term>
            <symbol> + </symbol>
            <term>
              <identifier> q </identifier>
            </term>
            <symbol> + </symbol>
            <term>
              <integerConstant> 1 </integerConstant>
            </term>
          </expression>
          <symbol> ; </symbol>
        </returnStatement>
      </statements>
      <symbol> } </symbol>
    </subroutineBody>
  </subroutineDec>
  <subroutineDec>
    <keyword> function </keyword>
    <keyword> int </keyword>
    <identifier> sqrt </identifier>
    <symbol> ( </symbol>
    <parameterList>
      <keyword> int </keyword>
      <identifier> x </identifier>
    </parameterList>
    <symbol> ) </symbol>
    <subroutineBody>
      <symbol> { </symbol>
      <varDec>
        <keyword> var </keyword>
        <keyword> int </keyword>
        <identifier> y </identifier>
        <symbol> , </symbol>
        <identifier> j </identifier>
        <symbol> , </symbol>
        <identifier> power2j </identifier>
        <symbol> ; </symbol>
      </varDec>
      <statements>
        <letStatement>
          <keyword> let </keyword>
          <identifier> y </identifier>
          <symbol> = </symbol>
          <expression>
            <term>
              <integerConstant> 0 </integerConstant>
            </term>
          </expression>
          <symbol> ; </symbol>
        </letStatement>
        <letStatement>
          <keyword> let </keyword>
          <identifier> j </identifier>
          <symbol> = </symbol>
          <expression>
            <term>
              <integerConstant> 7 </integerConstant>
            </term>
          </expression>
          <symbol> ; </symbol>
        </letStatement>
        <whileStatement>
          <keyword> while </keyword>
          <symbol> ( </symbol>
          <expression>
            <term>
              <identifier> j </identifier>
            </term>
            <symbol> &gt; </symbol>
            <term>
              <symbol> - </symbol>
              <term>
                <integerConstant> 1 </integerConstant>
              </term>
            </term>
          </expression>
          <symbol> ) </symbol>
          <symbol> { </symbol>
          <statements>
            <letStatement>
              <keyword> let </keyword>
              <identifier> power2j </identifier>
              <symbol> = </symbol>
              <expression>
                <term>
                  <subroutineCall>
                    <identifier> power </identifier>
                    <symbol> ( </symbol>
                    <expressionList>
                      <expression>
                        <term>
                          <integerConstant> 2 </integerConstant>
                        </term>
                      </expression>
                      <symbol> , </symbol>
                      <expression>
                        <term>
                          <identifier> j </identifier>
                        </term>
                      </expression>
                    </expressionList>
                    <symbol> ) </symbol>
                  </subroutineCall>
                </term>
              </expression>
              <symbol> ; </symbol>
            </letStatement>
            <ifStatement>
              <keyword> if </keyword>
              <symbol> ( </symbol>
              <expression>
                <term>
                  <symbol> ~ </symbol>
                  <term>
                    <symbol> ( </symbol>
                    <expression>
                      <term>
                        <subroutineCall>
                          <identifier> power </identifier>
                          <symbol> ( </symbol>
                          <expressionList>
                            <expression>
                              <term>
                                <identifier> y </identifier>
                              </term>
                              <symbol> + </symbol>
                              <term>
                                <identifier> power2j </identifier>
                              </term>
                            </expression>
                            <symbol> , </symbol>
                            <expression>
                              <term>
                                <integerConstant> 2 </integerConstant>
                              </term>
                            </expression>
                          </expressionList>
                          <symbol> ) </symbol>
                        </subroutineCall>
                      </term>
                      <symbol> &gt; </symbol>
                      <term>
                        <identifier> x </identifier>
                      </term>
                    </expression>
                    <symbol> ) </symbol>
                  </term>
                </term>
              </expression>
              <symbol> ) </symbol>
              <symbol> { </symbol>
              <statements>
                <letStatement>
                  <keyword> let </keyword>
                  <identifier> y </identifier>
                  <symbol> = </symbol>
                  <expression>
                    <term>
                      <identifier> y </identifier>
                    </term>
                    <symbol> + </symbol>
                    <term>
                      <identifier> power2j </identifier>
                    </term>
                  </expression>
                  <symbol> ; </symbol>
                </letStatement>
              </statements>
              <symbol> } </symbol>
            </ifStatement>
          </statements>
          <symbol> } </symbol>
        </whileStatement>
        <returnStatement>
          <keyword> return </keyword>
          <expression>
            <term>
              <identifier> y </identifier>
            </term>
          </expression>
          <symbol> ; </symbol>
        </returnStatement>
      </statements>
      <symbol> } </symbol>
    </subroutineBody>
  </subroutineDec>
  <subroutineDec>
    <keyword> function </keyword>
    <keyword> int </keyword>
    <identifier> power </identifier>
    <symbol> ( </symbol>
    <parameterList>
      <keyword> int </keyword>
      <identifier> a </identifier>
      <symbol> , </symbol>
      <keyword> int </keyword>
      <identifier> b </identifier>
    </parameterList>
    <symbol> ) </symbol>
    <subroutineBody>
      <symbol> { </symbol>
      <varDec>
        <keyword> var </keyword>
        <keyword> int </keyword>
        <identifier> result </identifier>
        <symbol> , </symbol>
        <identifier> count </identifier>
        <symbol> ; </symbol>
      </varDec>
      <statements>
        <letStatement>
          <keyword> let </keyword>
          <identifier> result </identifier>
          <symbol> = </symbol>
          <expression>
            <term>
              <identifier> a </identifier>
            </term>
          </expression>
          <symbol> ; </symbol>
        </letStatement>
        <letStatement>
          <keyword> let </keyword>
          <identifier> count </identifier>
          <symbol> = </symbol>
          <expression>
            <term>
              <identifier> b </identifier>
            </term>
          </expression>
          <symbol> ; </symbol>
        </letStatement>
        <whileStatement>
          <keyword> while </keyword>
          <symbol> ( </symbol>
          <expression>
            <term>
              <identifier> count </identifier>
            </term>
            <symbol> &gt; </symbol>
            <term>
              <integerConstant> 1 </integerConstant>
            </term>
          </expression>
          <symbol> ) </symbol>
          <symbol> { </symbol>
          <statements>
            <letStatement>
              <keyword> let </keyword>
              <identifier> result </identifier>
              <symbol> = </symbol>
              <expression>
                <term>
                  <identifier> result </identifier>
                </term>
                <symbol> * </symbol>
                <term>
                  <identifier> a </identifier>
                </term>
              </expression>
              <symbol> ; </symbol>
            </letStatement>
            <letStatement>
              <keyword> let </keyword>
              <identifier> count </identifier>
              <symbol> = </symbol>
              <expression>
                <term>
                  <identifier> count </identifier>
                </term>
                <symbol> - </symbol>
                <term>
                  <integerConstant> 1 </integerConstant>
                </term>
              </expression>
              <symbol> ; </symbol>
            </letStatement>
          </statements>
          <symbol> } </symbol>
        </whileStatement>
        <returnStatement>
          <keyword> return </keyword>
          <expression>
            <term>
              <identifier> result </identifier>
            </term>
          </expression>
          <symbol> ; </symbol>
        </returnStatement>
      </statements>
      <symbol> } </symbol>
    </subroutineBody>
  </subroutineDec>
  <subroutineDec>
    <keyword> function </keyword>
    <keyword> int </keyword>
    <identifier> max </identifier>
    <symbol> ( </symbol>
    <parameterList>
      <keyword> int </keyword>
      <identifier> a </identifier>
      <symbol> , </symbol>
      <keyword> int </keyword>
      <identifier> b </identifier>
    </parameterList>
    <symbol> ) </symbol>
    <subroutineBody>
      <symbol> { </symbol>
      <statements>
        <ifStatement>
          <keyword> if </keyword>
          <symbol> ( </symbol>
          <expression>
            <term>
              <identifier> a </identifier>
            </term>
            <symbol> &gt; </symbol>
            <term>
              <identifier> b </identifier>
            </term>
          </expression>
          <symbol> ) </symbol>
          <symbol> { </symbol>
          <statements>
            <returnStatement>
              <keyword> return </keyword>
              <expression>
                <term>
                  <identifier> a </identifier>
                </term>
              </expression>
              <symbol> ; </symbol>
            </returnStatement>
          </statements>
          <symbol> } </symbol>
        </ifStatement>
        <returnStatement>
          <keyword> return </keyword>
          <expression>
            <term>
              <identifier> b </identifier>
            </term>
          </expression>
          <symbol> ; </symbol>
        </returnStatement>
      </statements>
      <symbol> } </symbol>
    </subroutineBody>
  </subroutineDec>
  <subroutineDec>
    <keyword> function </keyword>
    <keyword> int </keyword>
    <identifier> min </identifier>
    <symbol> ( </symbol>
    <parameterList>
      <keyword> int </keyword>
      <identifier> a </identifier>
      <symbol> , </symbol>
      <keyword> int </keyword>
      <identifier> b </identifier>
    </parameterList>
    <symbol> ) </symbol>
    <subroutineBody>
      <symbol> { </symbol>
      <statements>
        <ifStatement>
          <keyword> if </keyword>
          <symbol> ( </symbol>
          <expression>
            <term>
              <identifier> a </identifier>
            </term>
            <symbol> &lt; </symbol>
            <term>
              <identifier> b </identifier>
            </term>
          </expression>
          <symbol> ) </symbol>
          <symbol> { </symbol>
          <statements>
            <returnStatement>
              <keyword> return </keyword>
              <expression>
                <term>
                  <identifier> a </identifier>
                </term>
              </expression>
              <symbol> ; </symbol>
            </returnStatement>
          </statements>
          <symbol> } </symbol>
        </ifStatement>
        <returnStatement>
          <keyword> return </keyword>
          <expression>
            <term>
              <identifier> b </identifier>
            </term>
          </expression>
          <symbol> ; </symbol>
        </returnStatement>
      </statements>
      <symbol> } </symbol>
    </subroutineBody>
  </subroutineDec>
  <symbol> } </symbol>
</class>
